[
  {
    "Name": "闪电质粒",
    "ShortName": "闪电质粒",
    "Color": "{default}",
    "HammerID": "3039",
    "GlowColor": [0,255,0,1],
    "BlockPickup": false,
    "AllowTransfer": true,
    "ForceDrop": true,
    "Chat": true,
    "Hud": true,
    "TriggerID": 0,
    "UsePriority": true,
    "AbilityList": [
      {
        "Name": "plasmid_button_electro",
        "ButtonID": 3040,
        "ButtonClass": "func_button",
        "Filter": "electrouser",
        "Chat_Uses": true,
        "Mode": 6,
        "MaxUses": 0,
        "CoolDown": 0,
        "Ignore": false,
        "LockItem": false,
        "MathID": 3046,
        "MathNameFix": false
      },
      {
        "Name": "plasmid_button_electro",
        "ButtonID": 3040,
        "ButtonClass": "func_button",
        "Filter": "electrouser",
        "Chat_Uses": true,
        "Mode": 2,
        "MaxUses": 0,
        "CoolDown": 11
      }
    ]
  },
  {
    "Name": "焚化质粒",
    "ShortName": "焚化质粒",
    "Color": "{default}",
    "HammerID": "3048",
    "GlowColor": [0,255,0,1],
    "BlockPickup": false,
    "AllowTransfer": true,
    "ForceDrop": true,
    "Chat": true,
    "Hud": true,
    "TriggerID": 0,
    "UsePriority": true,
    "AbilityList": [
      {
        "Name": "plasmid_button_incinerate",
        "ButtonID": 3049,
        "ButtonClass": "func_button",
        "Filter": "incinerateuser",
        "Chat_Uses": true,
        "Mode": 6,
        "MaxUses": 0,
        "CoolDown": 0,
        "Ignore": false,
        "LockItem": false,
        "MathID": 3055,
        "MathNameFix": false
      },
      {
        "Name": "plasmid_button_incinerate",
        "ButtonID": 3049,
        "ButtonClass": "func_button",
        "Filter": "incinerateuser",
        "Chat_Uses": true,
        "Mode": 2,
        "MaxUses": 0,
        "CoolDown": 5
      }
    ]
  },
  {
    "Name": "音爆质粒",
    "ShortName": "音爆质粒",
    "Color": "{default}",
    "HammerID": "3058",
    "GlowColor": [0,255,0,1],
    "BlockPickup": false,
    "AllowTransfer": true,
    "ForceDrop": true,
    "Chat": true,
    "Hud": true,
    "TriggerID": 0,
    "UsePriority": true,
    "AbilityList": [
      {
        "Name": "plasmid_button_cyclone",
        "ButtonID": 3059,
        "ButtonClass": "func_button",
        "Filter": "cycloneuser",
        "Chat_Uses": true,
        "Mode": 6,
        "MaxUses": 0,
        "CoolDown": 0,
        "Ignore": false,
        "LockItem": false,
        "MathID": 3065,
        "MathNameFix": false
      },
      {
        "Name": "plasmid_button_cyclone",
        "ButtonID": 3059,
        "ButtonClass": "func_button",
        "Filter": "cycloneuser",
        "Chat_Uses": true,
        "Mode": 2,
        "MaxUses": 0,
        "CoolDown": 10
      }
    ]
  },
  {
    "Name": "蜂群质粒",
    "ShortName": "蜂群质粒",
    "Color": "{default}",
    "HammerID": "3145",
    "GlowColor": [0,255,0,1],
    "BlockPickup": false,
    "AllowTransfer": true,
    "ForceDrop": true,
    "Chat": true,
    "Hud": true,
    "TriggerID": 0,
    "UsePriority": true,
    "AbilityList": [
      {
        "Name": "plasmid_button_insect",
        "ButtonID": 3146,
        "ButtonClass": "func_button",
        "Filter": "insectuser",
        "Chat_Uses": true,
        "Mode": 6,
        "MaxUses": 0,
        "CoolDown": 0,
        "Ignore": false,
        "LockItem": false,
        "MathID": 4334,
        "MathNameFix": false
      },
      {
        "Name": "plasmid_button_insect",
        "ButtonID": 3146,
        "ButtonClass": "func_button",
        "Filter": "insectuser",
        "Chat_Uses": true,
        "Mode": 2,
        "MaxUses": 0,
        "CoolDown": 10
      }
    ]
  },
  {
    "Name": "基因强化:闪电",
    "ShortName": "基因强化:闪电",
    "Color": "{default}",
    "HammerID": "3516",
    "GlowColor": [0,255,0,1],
    "BlockPickup": false,
    "AllowTransfer": false,
    "ForceDrop": false,
    "Chat": true,
    "Hud": true,
    "TriggerID": 0,
    "UsePriority": true,
    "AbilityList": [
      {
        "Name": "",
        "ButtonID": 0,
        "ButtonClass": "",
        "Filter": "",
        "Chat_Uses": true,
        "Mode": 1,
        "MaxUses": 0,
        "CoolDown": 0
      }
    ]
  },
  {
    "Name": "基因强化: 静电罩",
    "ShortName": "基因强化: 静电罩",
    "Color": "{default}",
    "HammerID": "3521",
    "GlowColor": [0,255,0,1],
    "BlockPickup": false,
    "AllowTransfer": false,
    "ForceDrop": false,
    "Chat": true,
    "Hud": true,
    "TriggerID": 0,
    "UsePriority": true,
    "AbilityList": [
      {
        "Name": "",
        "ButtonID": 0,
        "ButtonClass": "",
        "Filter": "",
        "Chat_Uses": true,
        "Mode": 1,
        "MaxUses": 0,
        "CoolDown": 0
      }
    ]
  },
  {
    "Name": "ZM 小妹妹",
    "ShortName": "ZM 小妹妹",
    "Color": "{default}",
    "HammerID": "3550",
    "GlowColor": [0,255,0,1],
    "BlockPickup": false,
    "AllowTransfer": false,
    "ForceDrop": false,
    "Chat": true,
    "Hud": true,
    "TriggerID": 0,
    "UsePriority": true,
    "AbilityList": [
      {
        "Name": "",
        "ButtonID": 0,
        "ButtonClass": "",
        "Filter": "little_sister",
        "Chat_Uses": true,
        "Mode": 6,
        "MaxUses": 0,
        "CoolDown": 0,
        "Ignore": false,
        "LockItem": false,
        "MathID": 3553,
        "MathNameFix": false
      }
    ]
  },
  {
    "Name": "ZM 大老爹",
    "ShortName": "ZM 大老爹",
    "Color": "{default}",
    "HammerID": "3557",
    "GlowColor": [0,255,0,1],
    "BlockPickup": false,
    "AllowTransfer": false,
    "ForceDrop": false,
    "Chat": true,
    "Hud": true,
    "TriggerID": 0,
    "UsePriority": true,
    "AbilityList": [
      {
        "Name": "",
        "ButtonID": 0,
        "ButtonClass": "",
        "Filter": "big_daddy",
        "Chat_Uses": true,
        "Mode": 1,
        "MaxUses": 0,
        "CoolDown": 0
      }
    ]
  },
  {
    "Name": "重力质粒",
    "ShortName": "重力质粒",
    "Color": "{default}",
    "HammerID": "4170",
    "GlowColor": [0,255,0,1],
    "BlockPickup": false,
    "AllowTransfer": true,
    "ForceDrop": true,
    "Chat": true,
    "Hud": true,
    "TriggerID": 0,
    "UsePriority": true,
    "AbilityList": [
      {
        "Name": "",
        "ButtonID": 0,
        "ButtonClass": "",
        "Filter": "",
        "Chat_Uses": true,
        "Mode": 6,
        "MaxUses": 0,
        "CoolDown": 0,
        "Ignore": false,
        "LockItem": false,
        "MathID": 4173,
        "MathNameFix": false
      },
      {
        "Name": "plasmid_button_gravity",
        "ButtonID": 4171,
        "ButtonClass": "func_button",
        "Filter": "gravityuser",
        "Chat_Uses": true,
        "Mode": 2,
        "MaxUses": 0,
        "CoolDown": 18
      }
    ]
  },
  {
    "Name": "寒霜质粒",
    "ShortName": "寒霜质粒",
    "Color": "{default}",
    "HammerID": "4182",
    "GlowColor": [0,255,0,1],
    "BlockPickup": false,
    "AllowTransfer": true,
    "ForceDrop": true,
    "Chat": true,
    "Hud": true,
    "TriggerID": 0,
    "UsePriority": true,
    "AbilityList": [
      {
        "Name": "plasmid_button_frost",
        "ButtonID": 4183,
        "ButtonClass": "func_button",
        "Filter": "frostuser",
        "Chat_Uses": true,
        "Mode": 6,
        "MaxUses": 0,
        "CoolDown": 0,
        "Ignore": false,
        "LockItem": false,
        "MathID": 4185,
        "MathNameFix": false
      },
      {
        "Name": "plasmid_button_frost",
        "ButtonID": 4183,
        "ButtonClass": "func_button",
        "Filter": "frostuser",
        "Chat_Uses": true,
        "Mode": 2,
        "MaxUses": 0,
        "CoolDown": 13
      }
    ]
  }
]