[
	{
		"Name": "红色火球/Red Fireball",
		"ShortName": "红色火球",
		"Color": "{default}",
		"HammerID": 36976,
		"GlowColor": [0,255,0,1],
		"BlockPickup": false,
		"AllowTransfer": true,
		"ForceDrop": true,
		"Chat": true,
		"Hud": true,
		"TriggerID": 0,
		"UsePriority": true,
		"AbilityList": [
			{
				"Name": "fireball_red_item_button",
				"ButtonID": 36983,
				"ButtonClass": "func_button",
				"Filter": "fireball_red_user:1",
				"Chat_Uses": true,
				"Mode": 2,
				"MaxUses": 0,
				"CoolDown": 20
			}
		]
	},
	{
		"Name": "绿色火球/Green Fireball",
		"ShortName": "绿色火球",
		"Color": "{default}",
		"HammerID": 37003,
		"GlowColor": [0,255,0,1],
		"BlockPickup": false,
		"AllowTransfer": true,
		"ForceDrop": true,
		"Chat": true,
		"Hud": true,
		"TriggerID": 0,
		"UsePriority": true,
		"AbilityList": [
			{
				"Name": "fireball_green_item_button",
				"ButtonID": 37008,
				"ButtonClass": "func_button",
				"Filter": "fireball_green_user:1",
				"Chat_Uses": true,
				"Mode": 2,
				"MaxUses": 0,
				"CoolDown": 20
			}
		]
	},
	{
		"Name": "蓝色火球/Blue Fireball",
		"ShortName": "蓝色火球",
		"Color": "{default}",
		"HammerID": 37092,
		"GlowColor": [0,255,0,1],
		"BlockPickup": false,
		"AllowTransfer": true,
		"ForceDrop": true,
		"Chat": true,
		"Hud": true,
		"TriggerID": 0,
		"UsePriority": true,
		"AbilityList": [
			{
				"Name": "fireball_blue_item_button",
				"ButtonID": 37097,
				"ButtonClass": "func_button",
				"Filter": "fireball_blue_user:1",
				"Chat_Uses": true,
				"Mode": 2,
				"MaxUses": 0,
				"CoolDown": 20
			}
		]
	},
	{
		"Name": "黄色火球/Yellow Fireball",
		"ShortName": "黄色火球",
		"Color": "{default}",
		"HammerID": 37110,
		"GlowColor": [0,255,0,1],
		"BlockPickup": false,
		"AllowTransfer": true,
		"ForceDrop": true,
		"Chat": true,
		"Hud": true,
		"TriggerID": 0,
		"UsePriority": true,
		"AbilityList": [
			{
				"Name": "fireball_yellow_item_button",
				"ButtonID": 37115,
				"ButtonClass": "func_button",
				"Filter": "fireball_yellow_user:1",
				"Chat_Uses": true,
				"Mode": 2,
				"MaxUses": 0,
				"CoolDown": 20
			}
		]
	},
	{
		"Name": "锤子/Hammer",
		"ShortName": "锤子",
		"Color": "{default}",
		"HammerID": 41946,
		"GlowColor": [0,255,0,1],
		"BlockPickup": false,
		"AllowTransfer": true,
		"ForceDrop": true,
		"Chat": true,
		"Hud": true,
		"TriggerID": 0,
		"UsePriority": true,
		"AbilityList": [
			{
				"Name": "",
				"ButtonID": 0,
				"ButtonClass": "",
				"Filter": "buildable:1",
				"Chat_Uses": false,
				"Mode": 1,
				"MaxUses": 0,
				"CoolDown": 0
			}
		]
	},
	{
		"Name": "终极/Warp",
		"ShortName": "终极",
		"Color": "{default}",
		"HammerID": 47686,
		"GlowColor": [0,255,0,1],
		"BlockPickup": false,
		"AllowTransfer": true,
		"ForceDrop": true,
		"Chat": true,
		"Hud": true,
		"TriggerID": 0,
		"UsePriority": true,
		"AbilityList": [
			{
				"Name": "warp_item_button",
				"ButtonID": 47687,
				"ButtonClass": "func_button",
				"Filter": "warp_user:1",
				"Chat_Uses": true,
				"Mode": 3,
				"MaxUses": 1,
				"CoolDown": 0
			}
		]
	},
	{
		"Name": "战利品/Loot",
		"ShortName": "战利品",
		"Color": "{default}",
		"HammerID": 47815,
		"GlowColor": [0,255,0,1],
		"BlockPickup": false,
		"AllowTransfer": true,
		"ForceDrop": true,
		"Chat": false,
		"Hud": true,
		"TriggerID": 0,
		"UsePriority": true,
		"AbilityList": [
			{
				"Name": "loot_item_button",
				"ButtonID": 47816,
				"ButtonClass": "func_button",
				"Filter": "loot_user:1",
				"Chat_Uses": false,
				"Mode": 2,
				"MaxUses": 0,
				"CoolDown": 5
			}
		]
	},
	{
		"Name": "火墙/Firewall",
		"ShortName": "火墙",
		"Color": "{default}",
		"HammerID": 47995,
		"GlowColor": [0,255,0,1],
		"BlockPickup": false,
		"AllowTransfer": true,
		"ForceDrop": true,
		"Chat": true,
		"Hud": true,
		"TriggerID": 0,
		"UsePriority": true,
		"AbilityList": [
			{
				"Name": "firewall_item_button",
				"ButtonID": 48002,
				"ButtonClass": "func_button",
				"Filter": "firewall_user:1",
				"Chat_Uses": true,
				"Mode": 2,
				"MaxUses": 0,
				"CoolDown": 90
			}
		]
	},
	{
		"Name": "水仙/Water Nymph",
		"ShortName": "水仙",
		"Color": "{default}",
		"HammerID": 48185,
		"GlowColor": [0,255,0,1],
		"BlockPickup": false,
		"AllowTransfer": true,
		"ForceDrop": true,
		"Chat": false,
		"Hud": true,
		"TriggerID": 0,
		"UsePriority": true,
		"AbilityList": [
			{
				"Name": "water_nymph_item_button",
				"ButtonID": 48186,
				"ButtonClass": "func_button",
				"Filter": "water_nymph_user:1",
				"Chat_Uses": false,
				"Mode": 1,
				"MaxUses": 0,
				"CoolDown": 0
			}
		]
	},
	{
		"Name": "钢管/metal pipe",
		"ShortName": "钢管",
		"Color": "{default}",
		"HammerID": 48636,
		"GlowColor": [0,255,0,1],
		"BlockPickup": false,
		"AllowTransfer": true,
		"ForceDrop": true,
		"Chat": true,
		"Hud": true,
		"TriggerID": 0,
		"UsePriority": true,
		"AbilityList": [
			{
				"Name": "metalpipe_item_b",
				"ButtonID": 48639,
				"ButtonClass": "func_button",
				"Filter": "metalpipe_user:1",
				"Chat_Uses": true,
				"Mode": 2,
				"MaxUses": 0,
				"CoolDown": 45
			}
		]
	},
	{
		"Name": "奶/Heal",
		"ShortName": "奶",
		"Color": "{default}",
		"HammerID": 36459,
		"GlowColor": [0,255,0,1],
		"BlockPickup": false,
		"AllowTransfer": true,
		"ForceDrop": true,
		"Chat": true,
		"Hud": true,
		"TriggerID": 0,
		"UsePriority": true,
		"AbilityList": [
			{
				"Name": "heal_item_button",
				"ButtonID": 36464,
				"ButtonClass": "func_button",
				"Filter": "heal_user:1",
				"Chat_Uses": true,
				"Mode": 2,
				"MaxUses": 0,
				"CoolDown": 60
			}
		]
	},
	{
		"Name": "火球/Flame",
		"ShortName": "火球",
		"Color": "{default}",
		"HammerID": 36478,
		"GlowColor": [0,255,0,1],
		"BlockPickup": false,
		"AllowTransfer": true,
		"ForceDrop": true,
		"Chat": true,
		"Hud": true,
		"TriggerID": 0,
		"UsePriority": true,
		"AbilityList": [
			{
				"Name": "flame_item_button",
				"ButtonID": 36485,
				"ButtonClass": "func_button",
				"Filter": "flame_user:1",
				"Chat_Uses": true,
				"Mode": 2,
				"MaxUses": 0,
				"CoolDown": 60
			}
		]
	},
	{
		"Name": "ZM 黑洞/Zombie Gravity",
		"ShortName": "ZM 黑洞",
		"Color": "{default}",
		"HammerID": 41673,
		"GlowColor": [0,255,0,1],
		"BlockPickup": false,
		"AllowTransfer": false,
		"ForceDrop": false,
		"Chat": true,
		"Hud": true,
		"TriggerID": 41705,
		"UsePriority": true,
		"AbilityList": [
			{
				"Name": "zm_gravity_item_button",
				"ButtonID": 41671,
				"ButtonClass": "func_button",
				"Filter": "zm_gravity_user:1",
				"Chat_Uses": true,
				"Mode": 2,
				"MaxUses": 0,
				"CoolDown": 90
			}
		]
	},
	{
		"Name": "ZM 奶/Zombie Heal",
		"ShortName": "ZM 奶",
		"Color": "{default}",
		"HammerID": 41694,
		"GlowColor": [0,255,0,1],
		"BlockPickup": false,
		"AllowTransfer": false,
		"ForceDrop": false,
		"Chat": true,
		"Hud": true,
		"TriggerID": 41704,
		"UsePriority": true,
		"AbilityList": [
			{
				"Name": "zm_heal_item_button",
				"ButtonID": 41697,
				"ButtonClass": "func_button",
				"Filter": "zm_heal_user:1",
				"Chat_Uses": true,
				"Mode": 2,
				"MaxUses": 0,
				"CoolDown": 90
			}
		]
	},
	{
		"Name": "ZM 飞行/Zombie Flight",
		"ShortName": "ZM 飞行",
		"Color": "{default}",
		"HammerID": 47771,
		"GlowColor": [0,255,0,1],
		"BlockPickup": false,
		"AllowTransfer": false,
		"ForceDrop": false,
		"Chat": true,
		"Hud": true,
		"TriggerID": 47772,
		"UsePriority": true,
		"AbilityList": [
			{
				"Name": "zm_flight_item_button",
				"ButtonID": 47776,
				"ButtonClass": "func_button",
				"Filter": "zm_flight_user:1",
				"Chat_Uses": true,
				"Mode": 2,
				"MaxUses": 0,
				"CoolDown": 45
			}
		]
	},
	{
		"Name": "ZM 火球/Zombie Fireball",
		"ShortName": "ZM 火球",
		"Color": "{default}",
		"HammerID": 47790,
		"GlowColor": [0,255,0,1],
		"BlockPickup": false,
		"AllowTransfer": false,
		"ForceDrop": false,
		"Chat": true,
		"Hud": true,
		"TriggerID": 47795,
		"UsePriority": true,
		"AbilityList": [
			{
				"Name": "zm_fireball_item_button",
				"ButtonID": 47793,
				"ButtonClass": "func_button",
				"Filter": "zm_fireball_user:1",
				"Chat_Uses": true,
				"Mode": 2,
				"MaxUses": 0,
				"CoolDown": 30
			}
		]
	}
]