[
  {
    "Name": "火",
    "ShortName": "火",
    "Color": "{default}",
    "HammerID": "1428",
    "GlowColor": [0,255,0,1],
    "BlockPickup": false,
    "AllowTransfer": true,
    "ForceDrop": true,
    "Chat": true,
    "Hud": true,
    "TriggerID": 0,
    "UsePriority": true,
    "AbilityList": [
      {
        "Name": "fire_button",
        "ButtonID": 1423,
        "ButtonClass": "func_button",
        "Filter": "Player_Fire",
        "Chat_Uses": true,
        "Mode": 2,
        "MaxUses": 0,
        "CoolDown": 60
      }
    ]
  },
  {
    "Name": "伤害",
    "ShortName": "伤害",
    "Color": "{default}",
    "HammerID": "1453",
    "GlowColor": [0,255,0,1],
    "BlockPickup": false,
    "AllowTransfer": true,
    "ForceDrop": true,
    "Chat": true,
    "Hud": true,
    "TriggerID": 0,
    "UsePriority": true,
    "AbilityList": [
      {
        "Name": "dmg_button",
        "ButtonID": 1451,
        "ButtonClass": "func_button",
        "Filter": "Player_Dmg",
        "Chat_Uses": true,
        "Mode": 2,
        "MaxUses": 0,
        "CoolDown": 30
      }
    ]
  },
  {
    "Name": "减速",
    "ShortName": "减速",
    "Color": "{default}",
    "HammerID": "1482",
    "GlowColor": [0,255,0,1],
    "BlockPickup": false,
    "AllowTransfer": true,
    "ForceDrop": true,
    "Chat": true,
    "Hud": true,
    "TriggerID": 0,
    "UsePriority": true,
    "AbilityList": [
      {
        "Name": "slow_button",
        "ButtonID": 1477,
        "ButtonClass": "func_button",
        "Filter": "Player_Slow",
        "Chat_Uses": true,
        "Mode": 2,
        "MaxUses": 0,
        "CoolDown": 60
      }
    ]
  },
  {
    "Name": "ZM 加速",
    "ShortName": "ZM 加速",
    "Color": "{default}",
    "HammerID": "1509",
    "GlowColor": [0,255,0,1],
    "BlockPickup": false,
    "AllowTransfer": false,
    "ForceDrop": false,
    "Chat": true,
    "Hud": true,
    "TriggerID": 2256,
    "UsePriority": true,
    "AbilityList": [
      {
        "Name": "zspeed_button",
        "ButtonID": 1506,
        "ButtonClass": "func_button",
        "Filter": "Player_ZSpeed",
        "Chat_Uses": true,
        "Mode": 2,
        "MaxUses": 0,
        "CoolDown": 60
      }
    ]
  },
  {
    "Name": "ZM 黑洞",
    "ShortName": "ZM 黑洞",
    "Color": "{default}",
    "HammerID": "1521",
    "GlowColor": [0,255,0,1],
    "BlockPickup": false,
    "AllowTransfer": false,
    "ForceDrop": false,
    "Chat": true,
    "Hud": true,
    "TriggerID": 2254,
    "UsePriority": true,
    "AbilityList": [
      {
        "Name": "zgravity_button",
        "ButtonID": 1519,
        "ButtonClass": "func_button",
        "Filter": "Player_ZGravity",
        "Chat_Uses": true,
        "Mode": 2,
        "MaxUses": 0,
        "CoolDown": 60
      }
    ]
  },
  {
    "Name": "蓝色钥匙",
    "ShortName": "蓝色钥匙",
    "Color": "{default}",
    "HammerID": "1877",
    "GlowColor": [0,255,0,1],
    "BlockPickup": false,
    "AllowTransfer": true,
    "ForceDrop": true,
    "Chat": true,
    "Hud": true,
    "TriggerID": 0,
    "UsePriority": true,
    "AbilityList": [
      {
        "Name": "",
        "ButtonID": 0,
        "ButtonClass": "",
        "Filter": "Player_key_blue",
        "Chat_Uses": true,
        "Mode": 0,
        "MaxUses": 0,
        "CoolDown": 0
      }
    ]
  },
  {
    "Name": "粉色钥匙",
    "ShortName": "粉色钥匙",
    "Color": "{default}",
    "HammerID": "1881",
    "GlowColor": [0,255,0,1],
    "BlockPickup": false,
    "AllowTransfer": true,
    "ForceDrop": true,
    "Chat": true,
    "Hud": true,
    "TriggerID": 0,
    "UsePriority": true,
    "AbilityList": [
      {
        "Name": "",
        "ButtonID": 0,
        "ButtonClass": "",
        "Filter": "Player_key_pink",
        "Chat_Uses": true,
        "Mode": 0,
        "MaxUses": 0,
        "CoolDown": 0
      }
    ]
  }
]