[
	{
		"Name": "push_elite",
		"ShortName": "push_elite",
		"Color": "{default}",
		"HammerID": "3926",
		"GlowColor": [0,255,0,1],
		"BlockPickup": false,
		"AllowTransfer": true,
		"ForceDrop": true,
		"Chat": true,
		"Hud": true,
		"TriggerID": 0,
		"UsePriority": true,
		"AbilityList": [
			{
				"Name": "weapon_elite",
				"ButtonID": 0,
				"ButtonClass": "",
				"Filter": "",
				"Chat_Uses": true,
				"Mode": 1,
				"MaxUses": 0,
				"CoolDown": 0
			}
		]
	},
	{
		"Name": "gravity_elite",
		"ShortName": "gravity_elite",
		"Color": "{default}",
		"HammerID": "3961",
		"GlowColor": [0,255,0,1],
		"BlockPickup": false,
		"AllowTransfer": true,
		"ForceDrop": true,
		"Chat": true,
		"Hud": true,
		"TriggerID": 0,
		"UsePriority": true,
		"AbilityList": [
			{
				"Name": "weapon_elite",
				"ButtonID": 0,
				"ButtonClass": "",
				"Filter": "",
				"Chat_Uses": true,
				"Mode": 1,
				"MaxUses": 0,
				"CoolDown": 0
			}
		]
	},
	{
		"Name": "zgravity_knife",
		"ShortName": "zgravity_knife",
		"Color": "{default}",
		"HammerID": "3987",
		"GlowColor": [0,255,0,1],
		"BlockPickup": false,
		"AllowTransfer": true,
		"ForceDrop": true,
		"Chat": true,
		"Hud": true,
		"TriggerID": 0,
		"UsePriority": true,
		"AbilityList": [
			{
				"Name": "weapon_knife",
				"ButtonID": 0,
				"ButtonClass": "",
				"Filter": "",
				"Chat_Uses": true,
				"Mode": 1,
				"MaxUses": 0,
				"CoolDown": 0
			}
		]
	},
	{
		"Name": "zheal_knife",
		"ShortName": "zheal_knife",
		"Color": "{default}",
		"HammerID": "3999",
		"GlowColor": [0,255,0,1],
		"BlockPickup": false,
		"AllowTransfer": true,
		"ForceDrop": true,
		"Chat": true,
		"Hud": true,
		"TriggerID": 0,
		"UsePriority": true,
		"AbilityList": [
			{
				"Name": "weapon_knife",
				"ButtonID": 0,
				"ButtonClass": "",
				"Filter": "",
				"Chat_Uses": true,
				"Mode": 1,
				"MaxUses": 0,
				"CoolDown": 0
			}
		]
	},
	{
		"Name": "laser_wall_elite",
		"ShortName": "laser_wall_elite",
		"Color": "{default}",
		"HammerID": "4010",
		"GlowColor": [0,255,0,1],
		"BlockPickup": false,
		"AllowTransfer": true,
		"ForceDrop": true,
		"Chat": true,
		"Hud": true,
		"TriggerID": 0,
		"UsePriority": true,
		"AbilityList": [
			{
				"Name": "weapon_elite",
				"ButtonID": 0,
				"ButtonClass": "",
				"Filter": "",
				"Chat_Uses": true,
				"Mode": 1,
				"MaxUses": 0,
				"CoolDown": 0
			}
		]
	},
	{
		"Name": "freezer_elite",
		"ShortName": "freezer_elite",
		"Color": "{default}",
		"HammerID": "4040",
		"GlowColor": [0,255,0,1],
		"BlockPickup": false,
		"AllowTransfer": true,
		"ForceDrop": true,
		"Chat": true,
		"Hud": true,
		"TriggerID": 0,
		"UsePriority": true,
		"AbilityList": [
			{
				"Name": "weapon_elite",
				"ButtonID": 0,
				"ButtonClass": "",
				"Filter": "",
				"Chat_Uses": true,
				"Mode": 1,
				"MaxUses": 0,
				"CoolDown": 0
			}
		]
	},
	{
		"Name": "zring_knife",
		"ShortName": "zring_knife",
		"Color": "{default}",
		"HammerID": "4046",
		"GlowColor": [0,255,0,1],
		"BlockPickup": false,
		"AllowTransfer": true,
		"ForceDrop": true,
		"Chat": true,
		"Hud": true,
		"TriggerID": 0,
		"UsePriority": true,
		"AbilityList": [
			{
				"Name": "weapon_knife",
				"ButtonID": 0,
				"ButtonClass": "",
				"Filter": "",
				"Chat_Uses": true,
				"Mode": 1,
				"MaxUses": 0,
				"CoolDown": 0
			}
		]
	},
	{
		"Name": "zfreeze_knife",
		"ShortName": "zfreeze_knife",
		"Color": "{default}",
		"HammerID": "4083",
		"GlowColor": [0,255,0,1],
		"BlockPickup": false,
		"AllowTransfer": true,
		"ForceDrop": true,
		"Chat": true,
		"Hud": true,
		"TriggerID": 0,
		"UsePriority": true,
		"AbilityList": [
			{
				"Name": "weapon_knife",
				"ButtonID": 0,
				"ButtonClass": "",
				"Filter": "",
				"Chat_Uses": true,
				"Mode": 1,
				"MaxUses": 0,
				"CoolDown": 0
			}
		]
	},
	{
		"Name": "zfire_knife",
		"ShortName": "zfire_knife",
		"Color": "{default}",
		"HammerID": "4101",
		"GlowColor": [0,255,0,1],
		"BlockPickup": false,
		"AllowTransfer": true,
		"ForceDrop": true,
		"Chat": true,
		"Hud": true,
		"TriggerID": 0,
		"UsePriority": true,
		"AbilityList": [
			{
				"Name": "weapon_knife",
				"ButtonID": 0,
				"ButtonClass": "",
				"Filter": "",
				"Chat_Uses": true,
				"Mode": 1,
				"MaxUses": 0,
				"CoolDown": 0
			}
		]
	},
	{
		"Name": "ammo_elite",
		"ShortName": "ammo_elite",
		"Color": "{default}",
		"HammerID": "4124",
		"GlowColor": [0,255,0,1],
		"BlockPickup": false,
		"AllowTransfer": true,
		"ForceDrop": true,
		"Chat": true,
		"Hud": true,
		"TriggerID": 0,
		"UsePriority": true,
		"AbilityList": [
			{
				"Name": "weapon_elite",
				"ButtonID": 0,
				"ButtonClass": "",
				"Filter": "",
				"Chat_Uses": true,
				"Mode": 1,
				"MaxUses": 0,
				"CoolDown": 0
			}
		]
	},
	{
		"Name": "human_canon_slow_elites",
		"ShortName": "human_canon_slow_elites",
		"Color": "{default}",
		"HammerID": "4167",
		"GlowColor": [0,255,0,1],
		"BlockPickup": false,
		"AllowTransfer": true,
		"ForceDrop": true,
		"Chat": true,
		"Hud": true,
		"TriggerID": 0,
		"UsePriority": true,
		"AbilityList": [
			{
				"Name": "weapon_elite",
				"ButtonID": 0,
				"ButtonClass": "",
				"Filter": "",
				"Chat_Uses": true,
				"Mode": 1,
				"MaxUses": 0,
				"CoolDown": 0
			}
		]
	},
	{
		"Name": "zslow_knife",
		"ShortName": "zslow_knife",
		"Color": "{default}",
		"HammerID": "4182",
		"GlowColor": [0,255,0,1],
		"BlockPickup": false,
		"AllowTransfer": true,
		"ForceDrop": true,
		"Chat": true,
		"Hud": true,
		"TriggerID": 0,
		"UsePriority": true,
		"AbilityList": [
			{
				"Name": "weapon_knife",
				"ButtonID": 0,
				"ButtonClass": "",
				"Filter": "",
				"Chat_Uses": true,
				"Mode": 1,
				"MaxUses": 0,
				"CoolDown": 0
			}
		]
	}
]