[
  {
    "Name": "ZM 蜘蛛/ZM Spider",
    "ShortName": "ZM 蜘蛛",
    "Color": "{default}",
    "HammerID": 1059,
    "GlowColor": [0,255,0,1],
    "BlockPickup": false,
    "AllowTransfer": false,
    "ForceDrop": false,
    "Chat": true,
    "Hud": true,
    "TriggerID": 1057,
    "UsePriority": true,
    "AbilityList": [
      {
        "Name": "",
        "ButtonID": 0,
        "ButtonClass": "",
        "Filter": "zombie",
        "Chat_Uses": true,
        "Mode": 0,
        "MaxUses": 0,
        "CoolDown": 0
      }
    ]
  },
  {
    "Name": "自爆猴子/Monkey",
    "ShortName": "猴子",
    "Color": "{default}",
    "HammerID": 1114,
    "GlowColor": [0,255,0,1],
    "BlockPickup": false,
    "AllowTransfer": true,
    "ForceDrop": true,
    "Chat": true,
    "Hud": true,
    "TriggerID": 0,
    "UsePriority": true,
    "AbilityList": [
      {
        "Name": "Item_Monkey_Button",
        "ButtonID": 1115,
        "ButtonClass": "func_physbox",
        "Filter": "user_bomb",
        "Chat_Uses": true,
        "Mode": 4,
        "MaxUses": 1,
        "CoolDown": 13
      }
    ]
  },
  {
    "Name": "ZM 火面条人/ZM Slenderfire",
    "ShortName": "ZM 火面条人",
    "Color": "{default}",
    "HammerID": 1257,
    "GlowColor": [0,255,0,1],
    "BlockPickup": false,
    "AllowTransfer": false,
    "ForceDrop": false,
    "Chat": true,
    "Hud": true,
    "TriggerID": 1259,
    "UsePriority": true,
    "AbilityList": [
      {
        "Name": "",
        "ButtonID": 0,
        "ButtonClass": "",
        "Filter": "zombie",
        "Chat_Uses": true,
        "Mode": 0,
        "MaxUses": 0,
        "CoolDown": 0
      }
    ]
  },
  {
    "Name": "ZM 面条人/ZM Slenderzombie",
    "ShortName": "ZM 面条人",
    "Color": "{default}",
    "HammerID": 357,
    "GlowColor": [0,255,0,1],
    "BlockPickup": false,
    "AllowTransfer": false,
    "ForceDrop": false,
    "Chat": true,
    "Hud": true,
    "TriggerID": 358,
    "UsePriority": true,
    "AbilityList": [
      {
        "Name": "",
        "ButtonID": 0,
        "ButtonClass": "",
        "Filter": "zombie",
        "Chat_Uses": true,
        "Mode": 0,
        "MaxUses": 0,
        "CoolDown": 0
      }
    ]
  },
  {
    "Name": "ZM 油桶/ZM Hide Barrel",
    "ShortName": "ZM 油桶",
    "Color": "{default}",
    "HammerID": 364,
    "GlowColor": [0,255,0,1],
    "BlockPickup": false,
    "AllowTransfer": false,
    "ForceDrop": false,
    "Chat": true,
    "Hud": true,
    "TriggerID": 360,
    "UsePriority": true,
    "AbilityList": [
      {
        "Name": "",
        "ButtonID": 0,
        "ButtonClass": "",
        "Filter": "hider",
        "Chat_Uses": true,
        "Mode": 0,
        "MaxUses": 0,
        "CoolDown": 0
      }
    ]
  },
  {
    "Name": "照明灯/Flashlight",
    "ShortName": "照明灯",
    "Color": "{default}",
    "HammerID": 248,
    "GlowColor": [0,255,0,1],
    "BlockPickup": false,
    "AllowTransfer": true,
    "ForceDrop": true,
    "Chat": false,
    "Hud": true,
    "TriggerID": 0,
    "UsePriority": true,
    "AbilityList": [
      {
        "Name": "Item_Flashlight_Button",
        "ButtonID": 246,
        "ButtonClass": "func_physbox",
        "Filter": "user_flashlight",
        "Chat_Uses": false,
        "Mode": 1,
        "MaxUses": 0,
        "CoolDown": 0
      }
    ]
  },
  {
    "Name": "荧光棒/Glowstick",
    "ShortName": "荧光棒",
    "Color": "{default}",
    "HammerID": 257,
    "GlowColor": [0,255,0,1],
    "BlockPickup": false,
    "AllowTransfer": true,
    "ForceDrop": true,
    "Chat": true,
    "Hud": true,
    "TriggerID": 0,
    "UsePriority": true,
    "AbilityList": [
      {
        "Name": "Item_Glowstick_Button",
        "ButtonID": 258,
        "ButtonClass": "func_physbox",
        "Filter": "glowstick",
        "Chat_Uses": true,
        "Mode": 2,
        "MaxUses": 0,
        "CoolDown": 25
      }
    ]
  },
  {
    "Name": "灯笼/Lantern",
    "ShortName": "灯笼",
    "Color": "{default}",
    "HammerID": 252,
    "GlowColor": [0,255,0,1],
    "BlockPickup": false,
    "AllowTransfer": true,
    "ForceDrop": true,
    "Chat": true,
    "Hud": true,
    "TriggerID": 0,
    "UsePriority": true,
    "AbilityList": [
      {
        "Name": "Item_Lantern_Button",
        "ButtonID": 250,
        "ButtonClass": "func_physbox",
        "Filter": "lantern",
        "Chat_Uses": true,
        "Mode": 2,
        "MaxUses": 0,
        "CoolDown": 42
      }
    ]
  },
  {
    "Name": "燃料/Fuel",
    "ShortName": "燃料",
    "Color": "{default}",
    "HammerID": 436,
    "GlowColor": [0,255,0,1],
    "BlockPickup": false,
    "AllowTransfer": true,
    "ForceDrop": true,
    "Chat": true,
    "Hud": false,
    "TriggerID": 0,
    "UsePriority": true,
    "AbilityList": [
      {
        "Name": "",
        "ButtonID": 0,
        "ButtonClass": "",
        "Filter": "",
        "Chat_Uses": true,
        "Mode": 0,
        "MaxUses": 0,
        "CoolDown": 0
      }
    ]
  },
  {
    "Name": "ZM 油桶王/ZM Barrelboss",
    "ShortName": "ZM 油桶王",
    "Color": "{default}",
    "HammerID": 595,
    "GlowColor": [0,255,0,1],
    "BlockPickup": false,
    "AllowTransfer": false,
    "ForceDrop": false,
    "Chat": true,
    "Hud": true,
    "TriggerID": 596,
    "UsePriority": true,
    "AbilityList": [
      {
        "Name": "",
        "ButtonID": 0,
        "ButtonClass": "",
        "Filter": "zombie",
        "Chat_Uses": true,
        "Mode": 0,
        "MaxUses": 0,
        "CoolDown": 0
      }
    ]
  }
]