[
	{
		"Name": "crossbow_knife",
		"ShortName": "crossbow_knife",
		"Color": "{default}",
		"HammerID": "102",
		"GlowColor": [
			255,
			255,
			255,
			255
		],
		"BlockPickup": false,
		"AllowTransfer": true,
		"ForceDrop": true,
		"Chat": true,
		"Hud": true,
		"TriggerID": 0,
		"UsePriority": true,
		"AbilityList": [
			{
				"Name": "weapon_knife",
				"ButtonID": 0,
				"ButtonClass": "",
				"Filter": "",
				"Chat_Uses": true,
				"Mode": 1,
				"MaxUses": 0,
				"CoolDown": 0
			}
		]
	},
	{
		"Name": "shotgun_elite",
		"ShortName": "shotgun_elite",
		"Color": "{default}",
		"HammerID": "93",
		"GlowColor": [
			255,
			255,
			255,
			255
		],
		"BlockPickup": false,
		"AllowTransfer": true,
		"ForceDrop": true,
		"Chat": true,
		"Hud": true,
		"TriggerID": 0,
		"UsePriority": true,
		"AbilityList": [
			{
				"Name": "weapon_glock",
				"ButtonID": 0,
				"ButtonClass": "",
				"Filter": "",
				"Chat_Uses": true,
				"Mode": 1,
				"MaxUses": 0,
				"CoolDown": 0
			}
		]
	},
	{
		"Name": "god_heal_elite",
		"ShortName": "god_heal_elite",
		"Color": "{default}",
		"HammerID": "150",
		"GlowColor": [
			255,
			255,
			255,
			255
		],
		"BlockPickup": false,
		"AllowTransfer": true,
		"ForceDrop": true,
		"Chat": true,
		"Hud": true,
		"TriggerID": 0,
		"UsePriority": true,
		"AbilityList": [
			{
				"Name": "weapon_glock",
				"ButtonID": 0,
				"ButtonClass": "",
				"Filter": "",
				"Chat_Uses": true,
				"Mode": 1,
				"MaxUses": 0,
				"CoolDown": 0
			}
		]
	},
	{
		"Name": "once_heal_elite",
		"ShortName": "once_heal_elite",
		"Color": "{default}",
		"HammerID": "66",
		"GlowColor": [
			255,
			255,
			255,
			255
		],
		"BlockPickup": false,
		"AllowTransfer": true,
		"ForceDrop": true,
		"Chat": true,
		"Hud": true,
		"TriggerID": 0,
		"UsePriority": true,
		"AbilityList": [
			{
				"Name": "weapon_glock",
				"ButtonID": 0,
				"ButtonClass": "",
				"Filter": "",
				"Chat_Uses": true,
				"Mode": 1,
				"MaxUses": 0,
				"CoolDown": 0
			}
		]
	}
]